simpler_graphrag/__init__.py
simpler_graphrag-2024.8.7.18.32.35.dist-info/LICENSE
simpler_graphrag-2024.8.7.18.32.35.dist-info/METADATA
simpler_graphrag-2024.8.7.18.32.35.dist-info/WHEEL
simpler_graphrag-2024.8.7.18.32.35.dist-info/entry_points.txt
simpler_graphrag-2024.8.7.18.32.35.dist-info/top_level.txt
simpler_graphrag-2024.8.7.18.32.35.dist-info/RECORD
