Metadata-Version: 2.1
Name: simpler_graphrag
Version: 2024.8.7.18.32.35
Summary: Create a Python package.
Home-page: https://github.com/yuanjie-ai/simpler_graphrag
Author: yuanjie
Author-email: 313303303@qq.com
License: MIT license
Keywords: simpler_graphrag
Classifier: Development Status :: 2 - Pre-Alpha
Classifier: Intended Audience :: Developers
Classifier: License :: OSI Approved :: MIT License
Classifier: Natural Language :: English
Classifier: Programming Language :: Python :: 3.7
Classifier: Programming Language :: Python :: 3.8
Requires-Python: >=3.7
License-File: LICENSE
Requires-Dist: meutils
Requires-Dist: openai
Requires-Dist: tiktoken
Requires-Dist: graphrag
Provides-Extra: all
